{
    "/js/jquery-ez-plus.js": "/js/jquery-ez-plus.js?id=ba3c7cada62de152fd8f",
    "/js/velocity-core.js": "/js/velocity-core.js?id=8010dfb021a49555afa7",
    "/js/velocity.js": "/js/velocity.js?id=ac05caeb5e4b0566a4ab",
    "/js/manifest.js": "/js/manifest.js?id=f801c7b774900481b564",
    "/js/components.js": "/js/components.js?id=d16d70d3905f32644901",
    "/css/velocity.css": "/css/velocity.css?id=075770f6dc71cf821f6c",
    "/css/velocity-admin.css": "/css/velocity-admin.css?id=f492100e7b8496e7b32d",
    "/images/Camera.svg": "/images/Camera.svg?id=b2fd2f9e17e1ccee96e2",
    "/images/Icon-Calendar.svg": "/images/Icon-Calendar.svg?id=870d0f733a5837742276",
    "/images/Icon-Crossed.svg": "/images/Icon-Crossed.svg?id=c72c3c1ef790bd4fd993",
    "/images/Icon-eye.svg": "/images/Icon-eye.svg?id=9345f20b862e21aa30c6",
    "/images/icon-search.svg": "/images/icon-search.svg?id=a5f38a895551b8a015b2"
}
